ggb/__init__.py
ggb/__main__.py
ggb/ggb.py
ggb/backend/__init__.py
ggb/backend/opencv_backend.py
ggb/backend/pil_backend.py
ggb/testing/__init__.py
ggb/testing/base.py
ggb/utils/__init__.py
ggb/utils/constant.py
ggb/utils/error.py
ggb/utils/image.py
ggb-1.1.5.dist-info/LICENSE
ggb-1.1.5.dist-info/METADATA
ggb-1.1.5.dist-info/WHEEL
ggb-1.1.5.dist-info/entry_points.txt
ggb-1.1.5.dist-info/top_level.txt
ggb-1.1.5.dist-info/RECORD
